{
    "version": "v1",
    "config": {
      "visState": {
        "filters": [],
        "layers": [
          {
            "id": "rdrwge",
            "type": "point",
            "config": {
              "dataId": "DESLOCAMENTOUK.csv",
              "label": "workplace",
              "color": [
                107,
                8,
                63
              ],
              "highlightColor": [
                252,
                242,
                26,
                255
              ],
              "columns": {
                "lat": "workplace_lat",
                "lng": "workplace_lng",
                "altitude": null
              },
              "isVisible": true,
              "visConfig": {
                "radius": 1,
                "fixedRadius": false,
                "opacity": 0.3,
                "outline": false,
                "thickness": 2,
                "strokeColor": null,
                "colorRange": {
                  "name": "Global Warming",
                  "type": "sequential",
                  "category": "Uber",
                  "colors": [
                    "#5A1846",
                    "#900C3F",
                    "#C70039",
                    "#E3611C",
                    "#F1920E",
                    "#FFC300"
                  ]
                },
                "strokeColorRange": {
                  "name": "Global Warming",
                  "type": "sequential",
                  "category": "Uber",
                  "colors": [
                    "#5A1846",
                    "#900C3F",
                    "#C70039",
                    "#E3611C",
                    "#F1920E",
                    "#FFC300"
                  ]
                },
                "radiusRange": [
                  0,
                  50
                ],
                "filled": true
              },
              "hidden": false,
              "textLabel": [
                {
                  "field": null,
                  "color": [
                    255,
                    255,
                    255
                  ],
                  "size": 18,
                  "offset": [
                    0,
                    0
                  ],
                  "anchor": "start",
                  "alignment": "center"
                }
              ]
            },
            "visualChannels": {
              "colorField": null,
              "colorScale": "quantile",
              "strokeColorField": null,
              "strokeColorScale": "quantile",
              "sizeField": null,
              "sizeScale": "linear"
            }
          },
          {
            "id": "faetyu",
            "type": "point",
            "config": {
              "dataId": "DESLOCAMENTOUK.csv",
              "label": "residence",
              "color": [
                250,
                161,
                0
              ],
              "highlightColor": [
                252,
                242,
                26,
                255
              ],
              "columns": {
                "lat": "residence_lat",
                "lng": "residence_lng",
                "altitude": null
              },
              "isVisible": true,
              "visConfig": {
                "radius": 1,
                "fixedRadius": false,
                "opacity": 0.3,
                "outline": false,
                "thickness": 2,
                "strokeColor": null,
                "colorRange": {
                  "name": "Global Warming",
                  "type": "sequential",
                  "category": "Uber",
                  "colors": [
                    "#5A1846",
                    "#900C3F",
                    "#C70039",
                    "#E3611C",
                    "#F1920E",
                    "#FFC300"
                  ]
                },
                "strokeColorRange": {
                  "name": "Global Warming",
                  "type": "sequential",
                  "category": "Uber",
                  "colors": [
                    "#5A1846",
                    "#900C3F",
                    "#C70039",
                    "#E3611C",
                    "#F1920E",
                    "#FFC300"
                  ]
                },
                "radiusRange": [
                  0,
                  50
                ],
                "filled": true
              },
              "hidden": false,
              "textLabel": [
                {
                  "field": null,
                  "color": [
                    255,
                    255,
                    255
                  ],
                  "size": 18,
                  "offset": [
                    0,
                    0
                  ],
                  "anchor": "start",
                  "alignment": "center"
                }
              ]
            },
            "visualChannels": {
              "colorField": null,
              "colorScale": "quantile",
              "strokeColorField": null,
              "strokeColorScale": "quantile",
              "sizeField": null,
              "sizeScale": "linear"
            }
          },
          {
            "id": "bgtfji",
            "type": "arc",
            "config": {
              "dataId": "DESLOCAMENTOUK.csv",
              "label": "workplace -> residence arc",
              "color": [
                200,
                117,
                0
              ],
              "highlightColor": [
                252,
                242,
                26,
                255
              ],
              "columns": {
                "lat0": "workplace_lat",
                "lng0": "workplace_lng",
                "lat1": "residence_lat",
                "lng1": "residence_lng"
              },
              "isVisible": true,
              "visConfig": {
                "opacity": 0.3,
                "thickness": 0.3,
                "colorRange": {
                  "name": "Global Warming",
                  "type": "sequential",
                  "category": "Uber",
                  "colors": [
                    "#5A1846",
                    "#900C3F",
                    "#C70039",
                    "#E3611C",
                    "#F1920E",
                    "#FFC300"
                  ]
                },
                "sizeRange": [
                  0,
                  10
                ],
                "targetColor": [
                  149,
                  12,
                  105
                ]
              },
              "hidden": false,
              "textLabel": [
                {
                  "field": null,
                  "color": [
                    255,
                    255,
                    255
                  ],
                  "size": 18,
                  "offset": [
                    0,
                    0
                  ],
                  "anchor": "start",
                  "alignment": "center"
                }
              ]
            },
            "visualChannels": {
              "colorField": null,
              "colorScale": "quantile",
              "sizeField": null,
              "sizeScale": "linear"
            }
          }
        ],
        "interactionConfig": {
          "tooltip": {
            "fieldsToShow": {
              "DESLOCAMENTOUK.csv": [
                {
                  "name": "all_flows",
                  "format": null
                }
              ]
            },
            "compareMode": false,
            "compareType": "absolute",
            "enabled": true
          },
          "brush": {
            "size": 0.5,
            "enabled": false
          },
          "geocoder": {
            "enabled": false
          },
          "coordinate": {
            "enabled": false
          }
        },
        "layerBlending": "additive",
        "splitMaps": [],
        "animationConfig": {
          "currentTime": null,
          "speed": 1
        }
      },
      "mapState": {
        "bearing": 24,
        "dragRotate": true,
        "latitude": 52.5670687263651,
        "longitude": -2.9155809690864882,
        "pitch": 50,
        "zoom": 4.859496452315544,
        "isSplit": false
      },
      "mapStyle": {
        "styleType": "dark",
        "topLayerGroups": {},
        "visibleLayerGroups": {
          "label": true,
          "road": true,
          "border": false,
          "building": true,
          "water": true,
          "land": true,
          "3d building": false
        },
        "threeDBuildingColor": [
          9.665468314072013,
          17.18305478057247,
          31.1442867897876
        ],
        "mapStyles": {}
      }
    }
  }